lightonml/__init__.py
lightonml/context.py
lightonml/datasets.py
lightonml/opu.py
lightonml/types.py
lightonml/utils.py
lightonml/cmd_line/__init__.py
lightonml/cmd_line/opu_test.py
lightonml/encoding/__init__.py
lightonml/encoding/base.py
lightonml/encoding/models.py
lightonml/internal/__init__.py
lightonml/internal/config.py
lightonml/internal/formatting.py
lightonml/internal/input_roi.py
lightonml/internal/inputdevice.py
lightonml/internal/inspect.py
lightonml/internal/output_roi.py
lightonml/internal/pidfile.py
lightonml/internal/popcount_u8.py
lightonml/internal/progress.py
lightonml/internal/runner.py
lightonml/internal/settings.py
lightonml/internal/simulated_device.py
lightonml/internal/test_utils.py
lightonml/internal/types.py
lightonml/internal/user_input.py
lightonml/internal/utils.py
lightonml/projections/__init__.py
lightonml/projections/sklearn.py
lightonml/projections/torch.py
lightonml-1.4.3.dist-info/LICENSE.txt
lightonml-1.4.3.dist-info/METADATA
lightonml-1.4.3.dist-info/WHEEL
lightonml-1.4.3.dist-info/entry_points.txt
lightonml-1.4.3.dist-info/top_level.txt
lightonml-1.4.3.dist-info/RECORD
