Metadata-Version: 2.1
Name: lightonml
Version: 1.4.3
Summary: LightOn technologies for Large scale Machine Learning with Optical Processing Unit
Home-page: https://docs.lighton.ai
Author: LightOn AI Research
Author-email: iacopo@lighton.io,charles@lighton.io,igor@lighton.io
License: UNKNOWN
Platform: UNKNOWN
Classifier: Programming Language :: Python
Classifier: Programming Language :: Python :: 3
Classifier: Programming Language :: Python :: 3.6
Classifier: Programming Language :: Python :: 3.7
Classifier: Programming Language :: Python :: 3.8
Classifier: Programming Language :: Python :: 3.9
Classifier: Topic :: Scientific/Engineering :: Artificial Intelligence
Classifier: Development Status :: 5 - Production/Stable
Classifier: Intended Audience :: Science/Research
Classifier: License :: OSI Approved :: Apache Software License
License-File: LICENSE.txt
Requires-Dist: numexpr (==2.7.*)
Requires-Dist: numpy
Requires-Dist: requests
Requires-Dist: attrs (>=19)
Provides-Extra: drivers
Requires-Dist: lightonopu (>=1.4.2) ; extra == 'drivers'
Provides-Extra: sklearn
Requires-Dist: scikit-learn ; extra == 'sklearn'
Provides-Extra: torch
Requires-Dist: torch (>=1.0) ; extra == 'torch'
